apptools/__init__.py
apptools/version.py
apptools/_testing/__init__.py
apptools/_testing/optional_dependencies.py
apptools/io/__init__.py
apptools/io/api.py
apptools/io/file.py
apptools/io/h5/__init__.py
apptools/io/h5/dict_node.py
apptools/io/h5/file.py
apptools/io/h5/table_node.py
apptools/io/h5/utils.py
apptools/io/h5/tests/__init__.py
apptools/io/h5/tests/test_dict_node.py
apptools/io/h5/tests/test_file.py
apptools/io/h5/tests/test_table_node.py
apptools/io/h5/tests/utils.py
apptools/io/tests/__init__.py
apptools/io/tests/test_file.py
apptools/io/tests/test_folder.py
apptools/logger/__init__.py
apptools/logger/api.py
apptools/logger/custom_excepthook.py
apptools/logger/log_point.py
apptools/logger/log_queue_handler.py
apptools/logger/logger.py
apptools/logger/ring_buffer.py
apptools/logger/agent/__init__.py
apptools/logger/agent/attachments.py
apptools/logger/agent/quality_agent_mailer.py
apptools/logger/agent/quality_agent_view.py
apptools/logger/agent/tests/__init__.py
apptools/logger/agent/tests/test_attachments.py
apptools/logger/plugin/__init__.py
apptools/logger/plugin/logger_plugin.py
apptools/logger/plugin/logger_preferences.py
apptools/logger/plugin/logger_service.py
apptools/logger/plugin/preferences.ini
apptools/logger/plugin/tests/__init__.py
apptools/logger/plugin/tests/test_logger_service.py
apptools/logger/plugin/view/__init__.py
apptools/logger/plugin/view/logger_preferences_page.py
apptools/logger/plugin/view/logger_view.py
apptools/logger/plugin/view/images/crit_error.png
apptools/logger/plugin/view/images/debug.png
apptools/logger/plugin/view/images/error.png
apptools/logger/plugin/view/images/info.png
apptools/logger/plugin/view/images/warning.png
apptools/naming/__init__.py
apptools/naming/address.py
apptools/naming/api.py
apptools/naming/binding.py
apptools/naming/context.py
apptools/naming/dir_context.py
apptools/naming/dynamic_context.py
apptools/naming/exception.py
apptools/naming/initial_context.py
apptools-5.3.0.dist-info/LICENSE.txt
apptools-5.3.0.dist-info/METADATA
apptools-5.3.0.dist-info/WHEEL
apptools-5.3.0.dist-info/top_level.txt
apptools-5.3.0.dist-info/RECORD
