Metadata-Version: 2.1
Name: apptools
Version: 5.3.0
Summary: application tools
Home-page: https://docs.enthought.com/apptools
Download-URL: https://www.github.com/enthought/apptools
Author: Enthought, Inc.
Author-email: info@enthought.com
Maintainer: ETS Developers
Maintainer-email: enthought-dev@enthought.com
License: BSD
Platform: Windows
Platform: Linux
Platform: Mac OS-X
Platform: Unix
Platform: Solaris
Classifier: Development Status :: 5 - Production/Stable
Classifier: Intended Audience :: Developers
Classifier: Intended Audience :: Science/Research
Classifier: License :: OSI Approved :: BSD License
Classifier: Operating System :: MacOS
Classifier: Operating System :: Microsoft :: Windows
Classifier: Operating System :: OS Independent
Classifier: Operating System :: POSIX
Classifier: Operating System :: Unix
Classifier: Programming Language :: Python
Classifier: Topic :: Scientific/Engineering
Classifier: Topic :: Software Development
Classifier: Topic :: Software Development :: Libraries
Requires-Python: >=3.8
License-File: LICENSE.txt
Requires-Dist: traits>=6.2.0
Provides-Extra: docs
Requires-Dist: enthought-sphinx-theme; extra == "docs"
Requires-Dist: sphinx; extra == "docs"
Provides-Extra: test
Requires-Dist: importlib-resources>=1.1.0; python_version < "3.9" and extra == "test"
Provides-Extra: gui
Requires-Dist: pyface; extra == "gui"
Requires-Dist: traitsui; extra == "gui"
Provides-Extra: h5
Requires-Dist: numpy<2.0; extra == "h5"
Requires-Dist: pandas; extra == "h5"
Requires-Dist: tables; extra == "h5"
Provides-Extra: persistence
Requires-Dist: numpy<2.0; extra == "persistence"
Provides-Extra: preferences
Requires-Dist: configobj; extra == "preferences"
